notification/__init__.py
notification/exceptions.py
notification/notifiers/__init__.py
notification/notifiers/pushover.py
notification/notifiers/webhook.py
python_notification-1.0.1.dist-info/LICENSE
python_notification-1.0.1.dist-info/METADATA
python_notification-1.0.1.dist-info/WHEEL
python_notification-1.0.1.dist-info/top_level.txt
python_notification-1.0.1.dist-info/RECORD
