Metadata-Version: 2.1
Name: python-notification
Version: 1.0.1
Summary: A Python library to send notifications
Home-page: https://github.com/jonghwanhyeon/python-notification
Author: Jonghwan Hyeon
Author-email: hyeon0145@gmail.com
License: UNKNOWN
Keywords: notification
Platform: UNKNOWN
Classifier: Development Status :: 4 - Beta
Classifier: Intended Audience :: Developers
Classifier: License :: OSI Approved :: MIT License
Classifier: Programming Language :: Python :: 3
Classifier: Programming Language :: Python :: 3.4
Classifier: Programming Language :: Python :: 3.5
Classifier: Programming Language :: Python :: 3.6
Classifier: Programming Language :: Python :: 3 :: Only
Classifier: Topic :: Communications
Classifier: Topic :: System :: Monitoring
Requires-Dist: requests
